{"_type":"export","__export_format":4,"__export_date":"2022-08-13T23:18:26.213Z","__export_source":"insomnia.desktop.app:v2022.4.2","resources":[{"_id":"req_22fd3bf565d44caabbf2237501e40afc","parentId":"wrk_bac739a83eeb412998f77bb51618cf1d","modified":1660013173665,"created":1660012596555,"url":"{{ _.base_url }}stores/createStore","name":"Hello","description":"","method":"GET","body":{},"parameters":[],"headers":[],"authentication":{},"metaSortKey":-1660012596555,"isPrivate":false,"settingStoreCookies":true,"settingSendCookies":true,"settingDisableRenderRequestBody":false,"settingEncodeUrl":true,"settingRebuildPath":true,"settingFollowRedirects":"global","_type":"request"},{"_id":"wrk_bac739a83eeb412998f77bb51618cf1d","parentId":null,"modified":1658359986492,"created":1658359986492,"name":"New Document","description":"","scope":"design","_type":"workspace"},{"_id":"req_a8cf895ae5c440b3be9115ca9114f0f5","parentId":"fld_7121095de90941be983cf058b4caa42b","modified":1660250776726,"created":1660014731215,"url":"{{ _.base_url }}users/login","name":"login","description":"","method":"POST","body":{"mimeType":"application/json","text":"{\n\t\"user\": {\n\t\t\"email\": \"ALEXIA.NAARA@GMAIL.COM\",\n\t\t\"senha\": \"111111\"\n\t}\n}"},"parameters":[],"headers":[{"name":"Content-Type","value":"application/json","id":"pair_3452987b725a4947ab9eeec9bd6668df"}],"authentication":{},"metaSortKey":-1660014731215,"isPrivate":false,"settingStoreCookies":true,"settingSendCookies":true,"settingDisableRenderRequestBody":false,"settingEncodeUrl":true,"settingRebuildPath":true,"settingFollowRedirects":"global","_type":"request"},{"_id":"fld_7121095de90941be983cf058b4caa42b","parentId":"wrk_bac739a83eeb412998f77bb51618cf1d","modified":1658360307343,"created":1658360307343,"name":"Users","description":"","environment":{},"environmentPropertyOrder":null,"metaSortKey":-1658360307343,"_type":"request_group"},{"_id":"req_9ffe513f2c264cbda527446930aea404","parentId":"fld_7121095de90941be983cf058b4caa42b","modified":1660014635939,"created":1658364161785,"url":"{{ _.base_url }}users/edit/2","name":"editUser","description":"","method":"PUT","body":{"mimeType":"application/json","text":"{\n\t\"name\": \"JOAO GOMES\",\n\t\"email\": \"JOAO.GOMES@GMAIL.COM\"\n}"},"parameters":[],"headers":[{"name":"Content-Type","value":"application/json","id":"pair_06bdb9fb7c5740d98de0b332b6c34b10"}],"authentication":{},"metaSortKey":-1658364161785,"isPrivate":false,"settingStoreCookies":true,"settingSendCookies":true,"settingDisableRenderRequestBody":false,"settingEncodeUrl":true,"settingRebuildPath":true,"settingFollowRedirects":"global","_type":"request"},{"_id":"req_3e1ab79330d64f3ba536d1b824699929","parentId":"fld_7121095de90941be983cf058b4caa42b","modified":1660090511573,"created":1658363508189,"url":"{{ _.base_url }}users/delete/3","name":"deleteUser","description":"","method":"DELETE","body":{},"parameters":[],"headers":[],"authentication":{},"metaSortKey":-1658363508189,"isPrivate":false,"settingStoreCookies":true,"settingSendCookies":true,"settingDisableRenderRequestBody":false,"settingEncodeUrl":true,"settingRebuildPath":true,"settingFollowRedirects":"global","_type":"request"},{"_id":"req_7059fd22f77e499381ce283976301eb4","parentId":"fld_7121095de90941be983cf058b4caa42b","modified":1660432655491,"created":1658360395611,"url":"{{ _.base_url }}users/register","name":"createUser","description":"","method":"POST","body":{"mimeType":"application/json","text":"{\n\t\"name\": \"Pedro Cavalcante\",\n\t\"email\": \"Pedro.Cavalcante@gmail.com\",\n\t\"cpf\": \"12546982356\",\n\t\"admin\": true,\n\t\"password\": \"111111\"\n}"},"parameters":[],"headers":[{"name":"Content-Type","value":"application/json","id":"pair_96b83f92ac56431fb1b012b466fe964d"}],"authentication":{},"metaSortKey":-1658360395611,"isPrivate":false,"settingStoreCookies":true,"settingSendCookies":true,"settingDisableRenderRequestBody":false,"settingEncodeUrl":true,"settingRebuildPath":true,"settingFollowRedirects":"global","_type":"request"},{"_id":"req_580cd5ecbc434cdbb2edaa7116ec3a9a","parentId":"fld_7121095de90941be983cf058b4caa42b","modified":1658360367996,"created":1658360350189,"url":"{{ _.base_url }}users/1","name":"getUsersById","description":"","method":"GET","body":{},"parameters":[],"headers":[],"authentication":{},"metaSortKey":-1658360350189,"isPrivate":false,"settingStoreCookies":true,"settingSendCookies":true,"settingDisableRenderRequestBody":false,"settingEncodeUrl":true,"settingRebuildPath":true,"settingFollowRedirects":"global","_type":"request"},{"_id":"req_86be5577474f478fa61693cdc94677d3","parentId":"fld_7121095de90941be983cf058b4caa42b","modified":1658360319147,"created":1658359986525,"url":"{{ _.base_url }}users","name":"getUsers","description":"","method":"GET","body":{},"parameters":[],"headers":[],"authentication":{},"metaSortKey":-1658359986525,"isPrivate":false,"settingStoreCookies":true,"settingSendCookies":true,"settingDisableRenderRequestBody":false,"settingEncodeUrl":true,"settingRebuildPath":true,"settingFollowRedirects":"global","_type":"request"},{"_id":"env_36f1ccb89f685e282f290ff76a8cc10c2ba7cde6","parentId":"wrk_bac739a83eeb412998f77bb51618cf1d","modified":1658360146605,"created":1658359986516,"name":"Base Environment","data":{},"dataPropertyOrder":{},"color":null,"isPrivate":false,"metaSortKey":1658359986516,"_type":"environment"},{"_id":"jar_36f1ccb89f685e282f290ff76a8cc10c2ba7cde6","parentId":"wrk_bac739a83eeb412998f77bb51618cf1d","modified":1658359986521,"created":1658359986521,"name":"Default Jar","cookies":[],"_type":"cookie_jar"},{"_id":"spc_7f7aed6fe34c492b8f5aa70e2dc18fb5","parentId":"wrk_bac739a83eeb412998f77bb51618cf1d","modified":1660432666304,"created":1658359986510,"fileName":"MDS","contents":"","contentType":"yaml","_type":"api_spec"},{"_id":"uts_1206eb8545ff434aa67c1d556c92f224","parentId":"wrk_bac739a83eeb412998f77bb51618cf1d","modified":1658359986527,"created":1658359986527,"name":"Example Test Suite","_type":"unit_test_suite"},{"_id":"env_3f6fdeeb096e42869c30af16e9a46415","parentId":"env_36f1ccb89f685e282f290ff76a8cc10c2ba7cde6","modified":1659137789028,"created":1658360140375,"name":"Capita-C","data":{"base_url":"http://localhost:4000/"},"dataPropertyOrder":{"&":["base_url"]},"color":"#e65656","isPrivate":false,"metaSortKey":1658360140375,"_type":"environment"}]}